applemusicpy/__init__.py
applemusicpy/client.py
apple_music_python-1.0.6.dist-info/LICENSE.txt
apple_music_python-1.0.6.dist-info/METADATA
apple_music_python-1.0.6.dist-info/WHEEL
apple_music_python-1.0.6.dist-info/top_level.txt
apple_music_python-1.0.6.dist-info/RECORD
