Metadata-Version: 2.1
Name: apple-music-python
Version: 1.0.6
Summary: A python wrapper for the Apple Music API
Home-page: https://github.com/mpalazzolo/apple-music-python
Author: Matt Palazzolo
Author-email: mattpalazzolo@gmail.com
License: LICENSE.txt
License-File: LICENSE.txt
Requires-Dist: requests >=2.21
Requires-Dist: pyjwt >=1.7.1
Requires-Dist: cryptography >=3.2
